<?xml version="1.0"?>
<productname>
	<servererror-tags>

		
		<servererror-tag name="mra.flown.msg.err.carriercodemandatory">
			<attribute name="clienterrorcode" value="mra.flown.msg.err.carriercodemandatory"/>
			<attribute name="objectarray" value=""/>
			<attribute name="errortype" value="ERROR"/>
		</servererror-tag>
		
		<servererror-tag name="mra.flown.msg.err.flightnumbermandatory">
			<attribute name="clienterrorcode" value="mra.flown.msg.err.flightnumbermandatory"/>
			<attribute name="objectarray" value=""/>
			<attribute name="errortype" value="ERROR"/>
		</servererror-tag>	
		<servererror-tag name="mra.flown.msg.err.flightdatemandatory">
			<attribute name="clienterrorcode" value="mra.flown.msg.err.flightdatemandatory"/>
			<attribute name="objectarray" value=""/>
			<attribute name="errortype" value="ERROR"/>
		</servererror-tag>
		
		<servererror-tag name="mra.flown.msg.err.entermandatoryfields">
			<attribute name="clienterrorcode" value="mra.flown.msg.err.entermandatoryfields"/>
			<attribute name="objectarray" value=""/>
			<attribute name="errortype" value="ERROR"/>
		</servererror-tag>
		
		<servererror-tag name="mra.flown.msg.err.noresultsfound">
			<attribute name="clienterrorcode" value="mra.flown.msg.err.noresultsfound"/>
			<attribute name="objectarray" value=""/>
			<attribute name="errortype" value="ERROR"/>
		</servererror-tag>
		
		<servererror-tag name="mra.flown.msg.err.invalidcarriercode">
			<attribute name="clienterrorcode" value="mra.flown.msg.err.invalidcarriercode"/>
			<attribute name="objectarray" value=""/>
			<attribute name="errortype" value="ERROR"/>
		</servererror-tag>


		<servererror-tag name="mra.flown.msg.err.invalidflight">
			<attribute name="clienterrorcode" value="mra.flown.msg.err.invalidflight"/>
			<attribute name="objectarray" value=""/>
			<attribute name="errortype" value="ERROR"/>
		</servererror-tag>

		<servererror-tag name="mra.flown.report.msg.err.invaliddaterange">
			<attribute name="clienterrorcode" value="mra.flown.report.msg.err.invaliddaterange"/>
			<attribute name="objectarray" value=""/>
			<attribute name="errortype" value="ERROR"/>
		</servererror-tag>

		<servererror-tag name="mra.flown.report.msg.err.invalidflight">
			<attribute name="clienterrorcode" value="mra.flown.report.msg.err.invalidflight"/>
			<attribute name="objectarray" value=""/>
			<attribute name="errortype" value="ERROR"/>
		</servererror-tag>


		<servererror-tag name="mailtracking.mra.flown.nodatafound">
			<attribute name="clienterrorcode" value="mailtracking.mra.flown.nodatafound"/>
			<attribute name="objectarray" value=""/>
			<attribute name="errortype" value="ERROR"/>
		</servererror-tag>

		<servererror-tag name="shared.airline.invalidairline">
			<attribute name="clienterrorcode" value="shared.airline.invalidairline"/>
			<attribute name="objectarray" value=""/>
			<attribute name="errortype" value="ERROR"/>
		</servererror-tag>
		
		
		<servererror-tag name="mailtracking.mra.flown.assignexceptions.msg.err.invalidfromDate">
			<attribute name="clienterrorcode" value="mailtracking.mra.flown.assignexceptions.msg.err.invalidfromDate"/>
			<attribute name="objectarray" value=""/>
			<attribute name="errortype" value="ERROR"/>
		</servererror-tag>
		
		<servererror-tag name="mailtracking.mra.flown.assignexceptions.msg.err.invalidDateRange">
			<attribute name="clienterrorcode" value="mailtracking.mra.flown.assignexceptions.msg.err.invalidDateRange"/>
			<attribute name="objectarray" value=""/>
			<attribute name="errortype" value="ERROR"/>
		</servererror-tag>
		
		<servererror-tag name="mailtracking.mra.flown.assignexceptios.msg.err.noresults">
			<attribute name="clienterrorcode" value="mailtracking.mra.flown.assignexceptios.msg.err.noresults"/>
			<attribute name="objectarray" value=""/>
			<attribute name="errortype" value="ERROR"/>
		</servererror-tag>
		
		<servererror-tag name="mailtracking.mra.flown.assignexceptios.msg.err.morethanonerowslected">
			<attribute name="clienterrorcode" value="mailtracking.mra.flown.assignexceptios.msg.err.morethanonerowslected"/>
			<attribute name="objectarray" value=""/>
			<attribute name="errortype" value="ERROR"/>
		</servererror-tag>
		
		<servererror-tag name="mailtracking.mra.flown.assignexceptions.msg.err.mandatoryfromdate">
			<attribute name="clienterrorcode" value="mailtracking.mra.flown.assignexceptions.msg.err.mandatoryfromdate"/>
			<attribute name="objectarray" value=""/>
			<attribute name="errortype" value="ERROR"/>
		</servererror-tag>
		
		<servererror-tag name="mailtracking.mra.flown.assignexceptios.msg.err.allinvalidusers">
			<attribute name="clienterrorcode" value="mailtracking.mra.flown.assignexceptios.msg.err.allinvalidusers"/>
			<attribute name="objectarray" value=""/>
			<attribute name="errortype" value="ERROR"/>
		</servererror-tag>
		
		<servererror-tag name="mailtracking.mra.flown.assignexceptios.msg.err.invalidusers">
			<attribute name="clienterrorcode" value="mailtracking.mra.flown.assignexceptios.msg.err.invalidusers"/>
			<attribute name="objectarray" value="0"/>
			<attribute name="errortype" value="ERROR"/>
		</servererror-tag>
		
		
		<servererror-tag name="mailtracking.mra.flown.processflight.procedure.notok">
			<attribute name="clienterrorcode" value="mailtracking.mra.flown.processflight.procedure.notok"/>
			<attribute name="objectarray" value="0"/>
			<attribute name="errortype" value="ERROR"/>
		</servererror-tag>
		
		<servererror-tag name="mailtracking.mra.flown.viewflownmail.norowselected">
			<attribute name="clienterrorcode" value="mailtracking.mra.flown.viewflownmail.norowselected"/>
			<attribute name="objectarray" value="0"/>
			<attribute name="errortype" value="ERROR"/>
		</servererror-tag>
		<servererror-tag name="mailtracking.mra.flown.processflight.processingsuccess">
			<attribute name="clienterrorcode" value="mailtracking.mra.flown.processflight.processingsuccess"/>
			<attribute name="objectarray" value="0"/>
			<attribute name="errortype" value="INFO"/>
		</servererror-tag>
		
		<!-- Added by A-5791 for ICRD-69710 Starts -->
		<servererror-tag name="mailtracking.mra.flown.report.NoDataFoundForMailRevenueDetails">
			<attribute name="clienterrorcode" value="mailtracking.mra.nodata"/>
			<attribute name="objectarray" value=""/>
			<attribute name="errortype" value="INFO"/>
		</servererror-tag>
		
		
		<servererror-tag name="mra.flown.mailRevenueReport.repgensuccess">
			<attribute name="clienterrorcode" value="mra.flown.mailRevenueReport.repgensuccess"/>
			<attribute name="objectarray" value=""/>
			<attribute name="errortype" value="INFO"/>
		</servererror-tag>
		<!-- Added by A-5791 for ICRD-69710 Ends -->
	</servererror-tags>
</productname>








